epubkit/__about__.py
epubkit/__init__.py
epubkit/backends.py
epubkit/cfi.py
epubkit/core.py
epubkit/hooks.py
epubkit/interfaces.py
epubkit/epub/metadata_parser.py
epubkit/epub/opf_parser.py
epubkit/epub/path_resolver.py
epubkit/epub/toc_builder.py
epubkit/epub/toc_parser.py
epubkit-0.1.0.post202601060842.dist-info/METADATA
epubkit-0.1.0.post202601060842.dist-info/WHEEL
epubkit-0.1.0.post202601060842.dist-info/licenses/LICENSE
epubkit-0.1.0.post202601060842.dist-info/RECORD
