Metadata-Version: 2.4
Name: epubkit
Version: 0.1.0.post202601060842
Summary: A comprehensive EPUB processing toolkit for Python
License: MIT License
License-File: LICENSE
Classifier: Development Status :: 3 - Alpha
Classifier: Intended Audience :: Developers
Classifier: License :: OSI Approved :: MIT License
Classifier: Operating System :: OS Independent
Classifier: Programming Language :: Python :: 3
Classifier: Programming Language :: Python :: 3.8
Classifier: Programming Language :: Python :: 3.9
Classifier: Programming Language :: Python :: 3.10
Classifier: Programming Language :: Python :: 3.11
Classifier: Programming Language :: Python :: 3.12
Classifier: Topic :: Software Development :: Libraries :: Python Modules
Classifier: Topic :: Text Processing :: Markup :: XML
Requires-Python: >=3.8
Requires-Dist: beautifulsoup4>=4.9.0
Requires-Dist: lxml>=4.9.0
Provides-Extra: cache
Requires-Dist: cachetools>=5.0.0; extra == 'cache'
